QuantGlobal/__init__.py
QuantGlobal/basecode.py
quantglobal-0.0.3.dist-info/METADATA
quantglobal-0.0.3.dist-info/WHEEL
quantglobal-0.0.3.dist-info/top_level.txt
quantglobal-0.0.3.dist-info/RECORD
