Metadata-Version: 2.1
Name: quantglobal
Version: 0.0.3
Summary: This package allows access to data provided by Quantitative Global.
Author: Quantitative Global Indices, LLC (Earl Charles)
Author-email: <echarles@qg-indices.com>
License: UNKNOWN
Keywords: python,quantitative finance,alternative data,statistics,stocks
Platform: UNKNOWN
Classifier: Programming Language :: Python :: 3
Classifier: Operating System :: OS Independent
Requires-Dist: pandas
Requires-Dist: requests
